{
	"costToBuild" : 
	[
		{
			"isPaid" : false,
			"type" : 2
		},
		{
			"isPaid" : false,
			"type" : 3
		},
		{
			"isPaid" : false,
			"type" : 3
		},
		{
			"isPaid" : false,
			"type" : 3
		},
		{
			"isPaid" : false,
			"type" : 3
		},
		{
			"isPaid" : false,
			"type" : 6
		}
	],
	"discardGain" : 3,
	"instantGain" : 
	[
		8
	],
	"isPaid" : false,
	"name" : "Inverseur de gravite",
	"numberOfCopies" : 1,
	"productionGain" : null,
	"quantityResourceMissing" : 6,
	"relativePathToTexture" : "./resources/img/Cards/Development_Cards/inverseur_de_gravite.png",
	"type" : 23,
	"victoryPoints" : 
	{
		"cardOrResourceType" : 24,
		"numberOfPoints" : 2
	}
}